LICENSE
MANIFEST.in
README.md
requirements.txt
setup.cfg
setup.py
ezaggrid/__init__.py
ezaggrid/__meta__.py
ezaggrid/params.py
ezaggrid/temp.py
ezaggrid/template.py
ezaggrid/util.py
ezaggrid/viewer.py
ezaggrid.egg-info/PKG-INFO
ezaggrid.egg-info/SOURCES.txt
ezaggrid.egg-info/dependency_links.txt
ezaggrid.egg-info/requires.txt
ezaggrid.egg-info/top_level.txt
ezaggrid/templates/compress.js
ezaggrid/templates/helpers.js
ezaggrid/templates/iframe.tpl.html
ezaggrid/templates/json.js
ezaggrid/templates/main.tpl.html
ezaggrid/templates/script.tpl.js