Metadata-Version: 1.1
Name: ezaggrid
Version: 0.2.4
Summary: display dataframe in ag-grid
Home-page: https://github.com/oscar6echo/ezaggrid
Author: oscar6echo
Author-email: olivier.borderies@gmail.com
License: MIT
Download-URL: https://github.com/oscar6echo/ezaggrid/tarball/0.2.4
Keywords: javascript,dataframe,ag-grid,display
Platform: UNKNOWN
Classifier: Development Status :: 4 - Beta
Classifier: License :: OSI Approved :: MIT License
Classifier: Programming Language :: Python :: 3.5
Classifier: Programming Language :: Python :: 3.6
